{"id":225,"name":"Deadpool 2","banner":"https://images7.alphacoders.com/901/thumb-1920-901925.jpg","rating":7.7,"desc":"Foul-mouthed mutant mercenary Wade Wilson (a.k.a. Deadpool), brings together a team of fellow mutant rogues to protect a young boy with supernatural abilities from the brutal, time-traveling cyborg Cable.","keywords":" Action, Adventure, Comedy ","poster":"https://m.media-amazon.com/images/M/MV5BNjk1Njk3YjctMmMyYS00Y2I4LThhMzktN2U0MTMyZTFlYWQ5XkEyXkFqcGdeQXVyODM2ODEzMDA@._V1_.jpg","episodes":[{"id":"1wHx-G-OD68u6h2THH9FdXj8bbkrvlYaG","name":"Deadpool 2","size":"2242367077"}],"type":"movie"}