{"id":89,"name":"Gladiator","banner":"https://wallpaperplay.com/walls/full/c/5/e/70493.jpg","rating":8.5,"desc":"A former Roman General sets out to exact vengeance against the corrupt emperor who murdered his family and sent him into slavery.","keywords":" Action, Adventure, Drama ","poster":"https://m.media-amazon.com/images/M/MV5BMDliMmNhNDEtODUyOS00MjNlLTgxODEtN2U3NzIxMGVkZTA1L2ltYWdlXkEyXkFqcGdeQXVyNjU0OTQ0OTY@._V1_SY1000_CR0,0,675,1000_AL_.jpg","episodes":[{"id":"1jh651QNizNRZkg42ChTO76zkLAAsSvdV","name":"Gladiator","size":"2861077808"}],"type":"movie"}